oignon/__init__.py
oignon/__main__.py
oignon/cli.py
oignon/server.py
oignon/tools.py
oignon/core/__init__.py
oignon/core/builder.py
oignon/core/graph.py
oignon/core/openalex.py
oignon/storage/__init__.py
oignon/storage/memory.py
mcp_oignon-0.1.3.dist-info/METADATA
mcp_oignon-0.1.3.dist-info/WHEEL
mcp_oignon-0.1.3.dist-info/entry_points.txt
mcp_oignon-0.1.3.dist-info/RECORD
