Metadata-Version: 2.4
Name: mcp-oignon
Version: 0.1.3
Summary: A lightweight, hand-crafted MCP server for exploring related literature and research
Project-URL: Homepage, https://github.com/hballington12/mcp-oignon
Project-URL: Repository, https://github.com/hballington12/mcp-oignon
Author-email: Harry Ballington <ballington@uni-wuppertal.de>
License-Expression: MIT
Keywords: academic,citations,knowledge,mcp,oignon,openalex,papers,reference,related-papers,research,scholar
Classifier: Development Status :: 4 - Beta
Classifier: License :: OSI Approved :: MIT License
Classifier: Programming Language :: Python :: 3
Classifier: Programming Language :: Python :: 3.11
Classifier: Programming Language :: Python :: 3.12
Classifier: Programming Language :: Python :: 3.13
Requires-Python: >=3.11
Requires-Dist: click>=8.0
Requires-Dist: mcp[cli]>=1.0.0
Requires-Dist: pyalex>=0.15
Provides-Extra: bench
Requires-Dist: claude-agent-sdk>=0.1.19; extra == 'bench'
Provides-Extra: dev
Requires-Dist: pyright>=1.1; extra == 'dev'
Requires-Dist: pytest>=8.0; extra == 'dev'
Requires-Dist: ruff>=0.7; extra == 'dev'
